runway/__init__.py
runway/_cli/__init__.py
runway/_cli/commands/__init__.py
runway/_cli/commands/_deploy.py
runway/_cli/commands/_destroy.py
runway/_cli/commands/_dismantle.py
runway/_cli/commands/_docs.py
runway/_cli/commands/_envvars.py
runway/_cli/commands/_gen_sample/__init__.py
runway/_cli/commands/_gen_sample/_cdk_csharp.py
runway/_cli/commands/_gen_sample/_cdk_py.py
runway/_cli/commands/_gen_sample/_cdk_tsc.py
runway/_cli/commands/_gen_sample/_cfn.py
runway/_cli/commands/_gen_sample/_cfngin.py
runway/_cli/commands/_gen_sample/_k8s_cfn_repo.py
runway/_cli/commands/_gen_sample/_k8s_flux_repo.py
runway/_cli/commands/_gen_sample/_k8s_tf_repo.py
runway/_cli/commands/_gen_sample/_sls_py.py
runway/_cli/commands/_gen_sample/_sls_tsc.py
runway/_cli/commands/_gen_sample/_static_angular.py
runway/_cli/commands/_gen_sample/_static_react.py
runway/_cli/commands/_gen_sample/_tf.py
runway/_cli/commands/_gen_sample/utils.py
runway/_cli/commands/_init.py
runway/_cli/commands/_kbenv/__init__.py
runway/_cli/commands/_kbenv/_install.py
runway/_cli/commands/_kbenv/_list.py
runway/_cli/commands/_kbenv/_run.py
runway/_cli/commands/_kbenv/_uninstall.py
runway/_cli/commands/_new.py
runway/_cli/commands/_plan.py
runway/_cli/commands/_preflight.py
runway/_cli/commands/_run_python.py
runway/_cli/commands/_schema/__init__.py
runway/_cli/commands/_schema/_cfngin.py
runway/_cli/commands/_schema/_runway.py
runway/_cli/commands/_takeoff.py
runway/_cli/commands/_taxi.py
runway/_cli/commands/_test.py
runway/_cli/commands/_tfenv/__init__.py
runway/_cli/commands/_tfenv/_install.py
runway/_cli/commands/_tfenv/_list.py
runway/_cli/commands/_tfenv/_run.py
runway/_cli/commands/_tfenv/_uninstall.py
runway/_cli/commands/_whichenv.py
runway/_cli/logs.py
runway/_cli/main.py
runway/_cli/options.py
runway/_cli/utils.py
runway/_logging.py
runway/aws_sso_botocore/__init__.py
runway/aws_sso_botocore/credentials.py
runway/aws_sso_botocore/exceptions.py
runway/aws_sso_botocore/session.py
runway-2.8.4.dist-info/LICENSE
runway-2.8.4.dist-info/METADATA
runway-2.8.4.dist-info/WHEEL
runway-2.8.4.dist-info/entry_points.txt
runway-2.8.4.dist-info/RECORD
