Metadata-Version: 2.3
Name: runway
Version: 2.8.4
Summary: Simplify infrastructure/app testing/deployment
License: Apache-2.0
Keywords: cli
Author: Rackspace Technology, Inc.
Author-email: opensource@rackspace.com
Maintainer: Kyle Finley
Maintainer-email: kyle@finley.sh
Requires-Python: >=3.9,<4.0
Classifier: Intended Audience :: Developers
Classifier: License :: OSI Approved :: Apache Software License
Classifier: Natural Language :: English
Classifier: Operating System :: OS Independent
Classifier: Programming Language :: Python :: 3
Classifier: Programming Language :: Python :: 3.9
Classifier: Programming Language :: Python :: 3.10
Classifier: Programming Language :: Python :: 3.11
Classifier: Programming Language :: Python :: 3.12
Classifier: Programming Language :: Python :: 3.13
Classifier: Topic :: Utilities
Requires-Dist: awacs
Requires-Dist: boto3 (>=1.34.50,<2.0.0)
Requires-Dist: cfn-lint
Requires-Dist: cfn_flip (>=1.2,<2.0)
Requires-Dist: click (>=8.0,<9.0)
Requires-Dist: coloredlogs (!=15.0.1)
Requires-Dist: docker (>=3.0.0)
Requires-Dist: eval-type-backport ; python_version < "3.10"
Requires-Dist: formic2
Requires-Dist: gitpython
Requires-Dist: igittigitt (>=2.0.5)
Requires-Dist: jinja2 (>=2.7)
Requires-Dist: packaging
Requires-Dist: pyOpenSSL
Requires-Dist: pydantic (>=2.8.0,<3.0.0)
Requires-Dist: pyhcl (>=0.4,<0.5)
Requires-Dist: python-hcl2 (>=3.0.0)
Requires-Dist: pyyaml (>5.4)
Requires-Dist: requests
Requires-Dist: tomli (>=1.2.2)
Requires-Dist: troposphere (>=2.4,<5)
Requires-Dist: typing_extensions
Requires-Dist: yamllint
Project-URL: Bug Tracker, https://github.com/rackspace/runway/issues
Project-URL: Documentation, https://runway.readthedocs.io
Project-URL: Homepage, https://github.com/rackspace/runway
Project-URL: Repository, https://github.com/rackspace/runway
